README.rst
setup.cfg
setup.py
stpl2/__init__.py
stpl2/internal.py
stpl2/tests.py
stpl2.egg-info/PKG-INFO
stpl2.egg-info/SOURCES.txt
stpl2.egg-info/dependency_links.txt
stpl2.egg-info/not-zip-safe
stpl2.egg-info/top_level.txt