Metadata-Version: 1.1
Name: stpl2
Version: 0.2.2
Summary: Fast and pythonic template engine
Home-page: https://github.com/ergoithz/stpl2
Author: Felipe A. Hernandez
Author-email: ergoithz@gmail.com
License: MIT
Download-URL: https://github.com/ergoithz/stpl2/tarball/0.2.2
Keywords: template,engine
Platform: any
Classifier: Development Status :: 4 - Beta
Classifier: Intended Audience :: Developers
Classifier: License :: OSI Approved :: MIT License
Classifier: Operating System :: OS Independent
Classifier: Programming Language :: Python
Classifier: Programming Language :: Python :: 3
Classifier: Topic :: Software Development :: Libraries :: Python Modules
